Metadata-Version: 2.4
Name: meu_investimento_re_2021
Version: 0.1
Summary: Uma biblioteca para cálculos de investimentos.
Home-page: https://github.com/tadrianonet/meu_investimento_re_2021
Author: renan melo
Author-email: renanfafasf@gmail.com
Classifier: Programming Language :: Python :: 3
Classifier: License :: OSI Approved :: MIT License
Classifier: Operating System :: OS Independent
Requires-Python: >=3.6
License-File: LICENSE
Dynamic: author
Dynamic: author-email
Dynamic: classifier
Dynamic: home-page
Dynamic: license-file
Dynamic: requires-python
Dynamic: summary
